changeplan/__init__.py
changeplan/change_plan_service.py
changeplan/middleware.py
changeplan-1.0.dist-info/METADATA
changeplan-1.0.dist-info/WHEEL
changeplan-1.0.dist-info/top_level.txt
changeplan-1.0.dist-info/RECORD
