Metadata-Version: 2.1
Name: changeplan
Version: 1.0
Summary: UNKNOWN
Home-page: UNKNOWN
Author: Julio Miranda
Author-email: dorlin_123@hotmail.com
License: UNKNOWN
Platform: UNKNOWN
Requires-Dist: requests
